Metadata-Version: 1.0
Name: ha-distributions
Version: 0.1
Summary: Gaussian and Binomial distributions
Home-page: UNKNOWN
Author: Hanny
Author-email: hanny.aly@gmail.com
License: UNKNOWN
Platform: UNKNOWN
